litestar_tus/__init__.py
litestar_tus/_utils.py
litestar_tus/backends/__init__.py
litestar_tus/backends/file.py
litestar_tus/backends/s3.py
litestar_tus/config.py
litestar_tus/controller.py
litestar_tus/events.py
litestar_tus/middleware.py
litestar_tus/models.py
litestar_tus/plugin.py
litestar_tus/protocols.py
litestar_tus-1.1.1.dist-info/WHEEL
litestar_tus-1.1.1.dist-info/METADATA
litestar_tus-1.1.1.dist-info/RECORD
