Metadata-Version: 2.4
Name: litestar-tus
Version: 1.1.1
Summary: TUS resumable upload protocol plugin for Litestar
Author: Enno Richter
Author-email: Enno Richter <enno@nerdworks.de>
License-Expression: MIT
Requires-Dist: litestar>=2.0
Requires-Dist: boto3>=1.35 ; extra == 's3'
Requires-Python: >=3.13
Provides-Extra: s3
